pygeko/__about__.py
pygeko/__init__.py
pygeko/gck_kriger.py
pygeko/gplot.py
pygeko/kdata.py
pygeko/kgrid.py
pygeko/lsgck.py
pygeko/models.py
pygeko/png_to_csv.py
pygeko/tempo.py
pygeko/utils.py
pygeko/examples/__init__.py
pygeko/examples/mb_restore_kdata.py
pygeko/examples/mb_save_kdata.py
pygeko/examples/mb_tune.py
pygeko/examples/mb_workflow.py
pygeko/examples/msh_restore_kdata.py
pygeko/examples/msh_save_kdata.py
pygeko/examples/msh_tune.py
pygeko/examples/msh_workflow.py
pygeko/testdata/montebea.csv
pygeko/testdata/msh5000.csv
pygeko-0.9.0.dist-info/METADATA
pygeko-0.9.0.dist-info/WHEEL
pygeko-0.9.0.dist-info/entry_points.txt
pygeko-0.9.0.dist-info/licenses/LICENSE
pygeko-0.9.0.dist-info/licenses/LICENSE.txt
pygeko-0.9.0.dist-info/RECORD
