Metadata-Version: 2.4
Name: pyGEKO
Version: 0.9.0
Summary: Fast Generalized Covariance Kriging for Python
Project-URL: Documentation, https://pygeko.readthedocs.io/
Project-URL: Issues, https://github.com/jccsvq/pygeko/issues
Project-URL: Source, https://github.com/jccsvq/pygeko
Author-email: Jesús Cabrera <jccsvq@gmail.com>
License: MIT
License-File: LICENSE
License-File: LICENSE.txt
Keywords: geostatistics,interpolation,kriging,raspberry-pi,spatial-analysis
Classifier: Development Status :: 4 - Beta
Classifier: Intended Audience :: Science/Research
Classifier: Programming Language :: Python :: 3.11
Classifier: Programming Language :: Python :: 3.12
Classifier: Topic :: Scientific/Engineering :: GIS
Requires-Python: >=3.11
Requires-Dist: joblib
Requires-Dist: matplotlib
Requires-Dist: numpy
Requires-Dist: pandas
Requires-Dist: plotly
Requires-Dist: psutil
Requires-Dist: scipy
Requires-Dist: seaborn
Requires-Dist: tqdm
